map_GL/__init__.py
map_GL/mapGL.py
map_GL/newick.py
mapGL-1.3.1.dist-info/LICENSE
mapGL-1.3.1.dist-info/METADATA
mapGL-1.3.1.dist-info/WHEEL
mapGL-1.3.1.dist-info/entry_points.txt
mapGL-1.3.1.dist-info/top_level.txt
mapGL-1.3.1.dist-info/RECORD
