Metadata-Version: 2.1
Name: mapGL
Version: 1.3.1
Summary: Prediction of lineage-specific gain and loss of sequence elements using phylogenetic maximum parsimony.
Home-page: https://github.com/adadiehl/mapGL
Author: Adam Diehl
Author-email: adadiehl@umich.edu
License: UNKNOWN
Keywords: phylogenetics,evolution,ancestral reconstruction
Platform: UNKNOWN
Classifier: Development Status :: 4 - Beta
Classifier: Programming Language :: Python :: 3
Classifier: License :: OSI Approved :: MIT License
Classifier: Operating System :: OS Independent
Classifier: Intended Audience :: Science/Research
Classifier: Topic :: Scientific/Engineering
Classifier: Topic :: Scientific/Engineering :: Information Analysis
Classifier: Natural Language :: English
Requires-Dist: numpy
Requires-Dist: six
Requires-Dist: bx-python
